.gitignore
CODE_OF_CONDUCT.md
LICENSE
README.md
requirements-client.txt
requirements-server.txt
setup.py
dardanelles/__init__.py
dardanelles/version.py
dardanelles.egg-info/PKG-INFO
dardanelles.egg-info/SOURCES.txt
dardanelles.egg-info/dependency_links.txt
dardanelles.egg-info/top_level.txt
dardanelles/client/__init__.py
dardanelles/server/__init__.py
dardanelles/server/app.py
dardanelles/server/bin.py
dardanelles/server/db.py
dardanelles/server/filesystem.py
tests/fixtures/Mobility-example.dfecf5bd.zip