Metadata-Version: 2.1
Name: dardanelles
Version: 0.1.dev0
Summary: Tool and web service for exchange of columnar life cycle inventory data
Home-page: https://github.com/brightway-lca/dardanelles
Author: Chris Mutel
Author-email: cmutel@gmail.com
License: BSD 3-clause
Classifier: Intended Audience :: End Users/Desktop
Classifier: Intended Audience :: Developers
Classifier: Intended Audience :: Science/Research
Classifier: License :: OSI Approved :: BSD License
Classifier: Operating System :: MacOS :: MacOS X
Classifier: Operating System :: Microsoft :: Windows
Classifier: Operating System :: POSIX
Classifier: Programming Language :: Python
Classifier: Programming Language :: Python :: 3
Classifier: Topic :: Scientific/Engineering :: Information Analysis
Classifier: Topic :: Scientific/Engineering :: Mathematics
Classifier: Topic :: Scientific/Engineering :: Visualization
License-File: LICENSE
